dls_bxflow_api/__init__.py
dls_bxflow_api/aiohttp_client.py
dls_bxflow_api/exceptions.py
dls_bxflow_api/remex.py
dls_bxflow_api/bx_databases/__init__.py
dls_bxflow_api/bx_databases/constants.py
dls_bxflow_api/bx_datafaces/__init__.py
dls_bxflow_api/bx_datafaces/aiohttp.py
dls_bxflow_api/bx_datafaces/bx_datafaces.py
dls_bxflow_api/bx_datafaces/constants.py
dls_bxflow_api/bx_datafaces/context.py
dls_bxflow_api/bx_launchers/constants.py
dls_bxflow_cli/__init__.py
dls_bxflow_cli/main.py
dls_bxflow_cli/version.py
dls_bxflow_cli/contexts/dataface_client.py
dls_bxflow_cli/contexts/filestore.py
dls_bxflow_cli/contexts/news_consumer.py
dls_bxflow_cli/subcommands/__init__.py
dls_bxflow_cli/subcommands/base.py
dls_bxflow_cli/subcommands/execute_workflow.py
dls_bxflow_cli/subcommands/find_xanes.py
dls_bxflow_cli/subcommands/fire_i22.py
dls_bxflow_cli/subcommands/recipe_parser.py
dls_bxflow_cli/subcommands/report_dcg.py
dls_bxflow_cli/subcommands/report_ispyb.py
dls_bxflow_cli/subcommands/start_services.py
dls_bxflow_cli/subcommands/submit.py
dls_bxflow_lib/__init__.py
dls_bxflow_lib/__main__.py
dls_bxflow_lib/_version.py
dls_bxflow_lib/base_aiohttp.py
dls_bxflow_lib/envvar.py
dls_bxflow_lib/typing.py
dls_bxflow_lib/version.py
dls_bxflow_lib/bx_catalogs/__init__.py
dls_bxflow_lib/bx_catalogs/aiohttp.py
dls_bxflow_lib/bx_catalogs/bx_catalogs.py
dls_bxflow_lib/bx_catalogs/constants.py
dls_bxflow_lib/bx_catalogs/context.py
dls_bxflow_lib/bx_catalogs/ispyb.py
dls_bxflow_lib/bx_collectors/__init__.py
dls_bxflow_lib/bx_collectors/aiohttp.py
dls_bxflow_lib/bx_collectors/base.py
dls_bxflow_lib/bx_collectors/bx_collectors.py
dls_bxflow_lib/bx_collectors/constants.py
dls_bxflow_lib/bx_collectors/context.py
dls_bxflow_lib/bx_collectors/gda_parser_base.py
dls_bxflow_lib/bx_collectors/gdascan.py
dls_bxflow_lib/bx_collectors/manual.py
dls_bxflow_lib/bx_collectors/scraper.py
dls_bxflow_lib/bx_composers/__init__.py
dls_bxflow_lib/bx_composers/bx_composers.py
dls_bxflow_lib/bx_composers/html.py
dls_bxflow-2.6.0.dist-info/LICENSE
dls_bxflow-2.6.0.dist-info/METADATA
dls_bxflow-2.6.0.dist-info/WHEEL
dls_bxflow-2.6.0.dist-info/entry_points.txt
dls_bxflow-2.6.0.dist-info/top_level.txt
dls_bxflow-2.6.0.dist-info/RECORD
